Metadata-Version: 2.1
Name: tadacnv
Version: 1.0.2
Summary: Annotation of TADs and CNVs
Home-page: https://github.com/jakob-he/TADA
Author: Jakob Hertzberg
Author-email: hertzber@molgen.mpg.de
License: UNKNOWN
Keywords: CNV Pathogencity Annotation TADs
Platform: UNKNOWN
Classifier: Programming Language :: Python :: 3.6
License-File: LICENSE
Requires-Dist: scipy (>=1.5)
Requires-Dist: numpy (>=1.19)
Requires-Dist: pandas (>=1.1)
Requires-Dist: matplotlib (>=3.3)
Requires-Dist: seaborn (>=0.11)
Requires-Dist: pyyaml (>=5.4)
Requires-Dist: networkx (>=2.5)
Requires-Dist: scikit-learn (>=0.24)
